{
  "_class": "shapePath",
  "booleanOperation": 3,
  "do_objectID": "030E2423-0409-46B3-9B8F-0BB33D1BCFD3",
  "edited": true,
  "exportOptions": {
    "_class": "exportOptions",
    "exportFormats": [
    ],
    "includedLayerIds": [
    ],
    "layerOptions": 0,
    "shouldTrim": false
  },
  "frame": {
    "_class": "rect",
    "constrainProportions": false,
    "height": 11,
    "width": 2.000000000000004,
    "x": 10,
    "y": 7
  },
  "isClosed": true,
  "isFlippedHorizontal": false,
  "isFlippedVertical": false,
  "isLocked": false,
  "isVisible": true,
  "layerListExpandedType": 0,
  "name": "Rectangle-path",
  "nameIsFixed": false,
  "pointRadiusBehaviour": 1,
  "points": [
    {
      "_class": "curvePoint",
      "cornerRadius": 0,
      "curveFrom": "{0, 0}",
      "curveMode": 1,
      "curveTo": "{0, 0}",
      "hasCurveFrom": false,
      "hasCurveTo": false,
      "point": "{0, 0}"
    },
    {
      "_class": "curvePoint",
      "cornerRadius": 0,
      "curveFrom": "{0, 1}",
      "curveMode": 1,
      "curveTo": "{0, 1}",
      "hasCurveFrom": false,
      "hasCurveTo": false,
      "point": "{0, 1}"
    },
    {
      "_class": "curvePoint",
      "cornerRadius": 0,
      "curveFrom": "{0.99999999999999822, 0.99999999999999967}",
      "curveMode": 1,
      "curveTo": "{0.99999999999999822, 0.99999999999999967}",
      "hasCurveFrom": false,
      "hasCurveTo": false,
      "point": "{0.99999999999999822, 0.99999999999999967}"
    },
    {
      "_class": "curvePoint",
      "cornerRadius": 0,
      "curveFrom": "{1, 8.0743492700011362e-17}",
      "curveMode": 1,
      "curveTo": "{1, 8.0743492700011362e-17}",
      "hasCurveFrom": false,
      "hasCurveTo": false,
      "point": "{1, 8.0743492700011362e-17}"
    }
  ],
  "resizingConstraint": 63,
  "resizingType": 0,
  "rotation": 0,
  "shouldBreakMaskChain": false
}