{
  "_class": "shapePath",
  "booleanOperation": 0,
  "do_objectID": "A52D58CF-FFC0-493C-A025-522AA72190B6",
  "edited": true,
  "exportOptions": {
    "_class": "exportOptions",
    "exportFormats": [
    ],
    "includedLayerIds": [
    ],
    "layerOptions": 0,
    "shouldTrim": false
  },
  "frame": {
    "_class": "rect",
    "constrainProportions": false,
    "height": 18,
    "width": 13,
    "x": 5,
    "y": 0
  },
  "isClosed": true,
  "isFlippedHorizontal": false,
  "isFlippedVertical": false,
  "isLocked": false,
  "isVisible": true,
  "layerListExpandedType": 0,
  "name": "Shape",
  "nameIsFixed": false,
  "pointRadiusBehaviour": 1,
  "points": [
    {
      "_class": "curvePoint",
      "cornerRadius": 0,
      "curveFrom": "{0.92307692307692313, 0.88888888888888884}",
      "curveMode": 4,
      "curveTo": "{0.9655603653715995, 0.88888888888888884}",
      "hasCurveFrom": false,
      "hasCurveTo": true,
      "point": "{0.92307692307692313, 0.88888888888888884}"
    },
    {
      "_class": "curvePoint",
      "cornerRadius": 0,
      "curveFrom": "{0.25716505773135556, 0.88888888888888884}",
      "curveMode": 4,
      "curveTo": "{0.38461538461538464, 0.88888888888888884}",
      "hasCurveFrom": true,
      "hasCurveTo": false,
      "point": "{0.38461538461538464, 0.88888888888888884}"
    },
    {
      "_class": "curvePoint",
      "cornerRadius": 0,
      "curveFrom": "{0.15384615384615385, 0.72222222222222221}",
      "curveMode": 4,
      "curveTo": "{0.15384615384615385, 0.81426968052735438}",
      "hasCurveFrom": false,
      "hasCurveTo": true,
      "point": "{0.15384615384615385, 0.72222222222222221}"
    },
    {
      "_class": "curvePoint",
      "cornerRadius": 0,
      "curveFrom": "{0.15384615384615385, 0.024873069453844807}",
      "curveMode": 4,
      "curveTo": "{0.15384615384615385, 0.055555555555555552}",
      "hasCurveFrom": true,
      "hasCurveTo": false,
      "point": "{0.15384615384615385, 0.055555555555555552}"
    },
    {
      "_class": "curvePoint",
      "cornerRadius": 0,
      "curveFrom": "{0.034439634628400523, 0}",
      "curveMode": 2,
      "curveTo": "{0.11940651921775333, 0}",
      "hasCurveFrom": true,
      "hasCurveTo": true,
      "point": "{0.076923076923076927, 0}"
    },
    {
      "_class": "curvePoint",
      "cornerRadius": 0,
      "curveFrom": "{0, 0.055555555555555552}",
      "curveMode": 4,
      "curveTo": "{0, 0.024873069453844807}",
      "hasCurveFrom": false,
      "hasCurveTo": true,
      "point": "{0, 0.055555555555555552}"
    },
    {
      "_class": "curvePoint",
      "cornerRadius": 0,
      "curveFrom": "{0, 0.8756346527307759}",
      "curveMode": 4,
      "curveTo": "{0, 0.72222222222222221}",
      "hasCurveFrom": true,
      "hasCurveTo": false,
      "point": "{0, 0.72222222222222221}"
    },
    {
      "_class": "curvePoint",
      "cornerRadius": 0,
      "curveFrom": "{0.38461538461538464, 1}",
      "curveMode": 4,
      "curveTo": "{0.17219817314200253, 1}",
      "hasCurveFrom": false,
      "hasCurveTo": true,
      "point": "{0.38461538461538464, 1}"
    },
    {
      "_class": "curvePoint",
      "cornerRadius": 0,
      "curveFrom": "{0.9655603653715995, 1}",
      "curveMode": 4,
      "curveTo": "{0.92307692307692313, 1}",
      "hasCurveFrom": true,
      "hasCurveTo": false,
      "point": "{0.92307692307692313, 1}"
    },
    {
      "_class": "curvePoint",
      "cornerRadius": 0,
      "curveFrom": "{1, 0.91376195834273366}",
      "curveMode": 2,
      "curveTo": "{1, 0.97512693054615518}",
      "hasCurveFrom": true,
      "hasCurveTo": true,
      "point": "{1, 0.94444444444444442}"
    }
  ],
  "resizingConstraint": 63,
  "resizingType": 0,
  "rotation": 0,
  "shouldBreakMaskChain": false
}