{
  "_class": "shapeGroup",
  "clippingMaskMode": 0,
  "do_objectID": "B938EE45-F842-4E02-9325-75294F45B083",
  "exportOptions": {
    "_class": "exportOptions",
    "exportFormats": [
    ],
    "includedLayerIds": [
    ],
    "layerOptions": 0,
    "shouldTrim": false
  },
  "frame": {
    "_class": "rect",
    "constrainProportions": false,
    "height": 22,
    "width": 18,
    "x": 3,
    "y": 1
  },
  "hasClickThrough": false,
  "hasClippingMask": true,
  "isFlippedHorizontal": false,
  "isFlippedVertical": false,
  "isLocked": false,
  "isVisible": true,
  "layerListExpandedType": 0,
  "layers": [
    {
      "class": "shapePath",
      "id": "6695E28A-AB2F-49F2-9809-C4B31CD75B06"
    },
    {
      "class": "shapePath",
      "id": "EA3F5DF9-9DE1-4332-83B3-11AB2F61C743"
    },
    {
      "class": "shapePath",
      "id": "CDB615F4-46CD-4BF0-BFF1-D1123146ACA6"
    }
  ],
  "name": "Combined Shape",
  "nameIsFixed": false,
  "resizingConstraint": 63,
  "resizingType": 0,
  "rotation": 0,
  "shouldBreakMaskChain": false,
  "style": {
    "_class": "style",
    "endDecorationType": 0,
    "fills": [
      {
        "_class": "fill",
        "color": {
          "_class": "color",
          "alpha": 1,
          "blue": 0,
          "green": 0,
          "red": 0
        },
        "fillType": 0,
        "isEnabled": true,
        "noiseIndex": 0,
        "noiseIntensity": 0,
        "patternFillType": 1,
        "patternTileScale": 1
      }
    ],
    "miterLimit": 10,
    "startDecorationType": 0
  },
  "windingRule": 0
}