{
  "_class": "shapePath",
  "booleanOperation": -1,
  "do_objectID": "6A4A5FEE-91E6-46C5-B984-09D900FE42C6",
  "edited": true,
  "exportOptions": {
    "_class": "exportOptions",
    "exportFormats": [
    ],
    "includedLayerIds": [
    ],
    "layerOptions": 0,
    "shouldTrim": false
  },
  "frame": {
    "_class": "rect",
    "constrainProportions": false,
    "height": 18,
    "width": 14,
    "x": 2,
    "y": 2
  },
  "isClosed": true,
  "isFlippedHorizontal": false,
  "isFlippedVertical": false,
  "isLocked": false,
  "isVisible": true,
  "layerListExpandedType": 0,
  "name": "Path",
  "nameIsFixed": false,
  "pointRadiusBehaviour": 1,
  "points": [
    {
      "_class": "curvePoint",
      "cornerRadius": 0,
      "curveFrom": "{0.031979660726371879, 0}",
      "curveMode": 4,
      "curveTo": "{0.071428571428571425, 0}",
      "hasCurveFrom": true,
      "hasCurveTo": false,
      "point": "{0.071428571428571425, 0}"
    },
    {
      "_class": "curvePoint",
      "cornerRadius": 0,
      "curveFrom": "{0, 0.055555555555555552}",
      "curveMode": 4,
      "curveTo": "{0, 0.02487306945384482}",
      "hasCurveFrom": false,
      "hasCurveTo": true,
      "point": "{0, 0.055555555555555552}"
    },
    {
      "_class": "curvePoint",
      "cornerRadius": 0,
      "curveFrom": "{0, 0.9751269305461554}",
      "curveMode": 4,
      "curveTo": "{0, 0.94444444444444442}",
      "hasCurveFrom": true,
      "hasCurveTo": false,
      "point": "{0, 0.94444444444444442}"
    },
    {
      "_class": "curvePoint",
      "cornerRadius": 0,
      "curveFrom": "{0.071428571428571425, 1}",
      "curveMode": 4,
      "curveTo": "{0.031979660726371782, 1}",
      "hasCurveFrom": false,
      "hasCurveTo": true,
      "point": "{0.071428571428571425, 1}"
    },
    {
      "_class": "curvePoint",
      "cornerRadius": 0,
      "curveFrom": "{0.96802033927362807, 1}",
      "curveMode": 4,
      "curveTo": "{0.9285714285714286, 1}",
      "hasCurveFrom": true,
      "hasCurveTo": false,
      "point": "{0.9285714285714286, 1}"
    },
    {
      "_class": "curvePoint",
      "cornerRadius": 0,
      "curveFrom": "{1, 0.94444444444444442}",
      "curveMode": 4,
      "curveTo": "{1, 0.97512693054615496}",
      "hasCurveFrom": false,
      "hasCurveTo": true,
      "point": "{1, 0.94444444444444442}"
    },
    {
      "_class": "curvePoint",
      "cornerRadius": 0,
      "curveFrom": "{1, 0.024873069453844893}",
      "curveMode": 4,
      "curveTo": "{1, 0.055555555555555532}",
      "hasCurveFrom": true,
      "hasCurveTo": false,
      "point": "{1, 0.055555555555555532}"
    },
    {
      "_class": "curvePoint",
      "cornerRadius": 0,
      "curveFrom": "{0.9285714285714286, 0}",
      "curveMode": 4,
      "curveTo": "{0.96802033927362796, 0}",
      "hasCurveFrom": false,
      "hasCurveTo": true,
      "point": "{0.9285714285714286, 0}"
    }
  ],
  "resizingConstraint": 63,
  "resizingType": 0,
  "rotation": 0,
  "shouldBreakMaskChain": false
}